mergefields.py
docx_mergefields-0.1.3.dist-info/LICENSE
docx_mergefields-0.1.3.dist-info/METADATA
docx_mergefields-0.1.3.dist-info/WHEEL
docx_mergefields-0.1.3.dist-info/top_level.txt
docx_mergefields-0.1.3.dist-info/RECORD
