Metadata-Version: 2.1
Name: docx-mergefields
Version: 0.1.3
Summary: Replaces fields in docx (Microsoft Office Word) files
Home-page: http://github.com/iulica/docx-mergefields
Author: Iulian Ciorăscu
Author-email: ciulian@gmail.com
License: MIT
Classifier: License :: OSI Approved :: MIT License
Classifier: Programming Language :: Python :: 3.7
Classifier: Topic :: Text Processing
License-File: LICENSE
Requires-Dist: python-docx
